hytopia_mcp/__init__.py
hytopia_mcp/cli.py
hytopia_mcp/config.py
hytopia_mcp/server.py
hytopia_mcp/resources/__init__.py
hytopia_mcp/resources/api_resources.py
hytopia_mcp/tools/__init__.py
hytopia_mcp/tools/api_explorer.py
hytopia_mcp/tools/concept_explainer.py
hytopia_mcp/tools/documentation.py
hytopia_mcp/tools/example_analyzer.py
hytopia_mcp/tools/pattern_analyzer.py
hytopia_mcp/tools/sdk_updater.py
hytopia_mcp/tools/search_tools.py
hytopia_mcp/utils/__init__.py
hytopia_mcp/utils/cache_manager.py
hytopia_mcp/utils/sdk_analyzer.py
hytopia_mcp-1.0.1.dist-info/METADATA
hytopia_mcp-1.0.1.dist-info/WHEEL
hytopia_mcp-1.0.1.dist-info/entry_points.txt
hytopia_mcp-1.0.1.dist-info/licenses/LICENSE
hytopia_mcp-1.0.1.dist-info/RECORD
