Metadata-Version: 2.4
Name: hytopia-mcp
Version: 1.0.1
Summary: MCP server for HYTOPIA SDK - Optimized for Claude Code development
Project-URL: Homepage, https://github.com/AnrokX/hytopia-mcp
Project-URL: Documentation, https://github.com/AnrokX/hytopia-mcp#readme
Project-URL: Repository, https://github.com/AnrokX/hytopia-mcp
Project-URL: Issues, https://github.com/AnrokX/hytopia-mcp/issues
Author-email: HYTOPIA Community <support@hytopia.com>
License: MIT
License-File: LICENSE
Keywords: claude,gamedev,hytopia,mcp,sdk,voxel
Classifier: Development Status :: 4 - Beta
Classifier: Intended Audience :: Developers
Classifier: License :: OSI Approved :: MIT License
Classifier: Programming Language :: Python :: 3
Classifier: Programming Language :: Python :: 3.10
Classifier: Programming Language :: Python :: 3.11
Classifier: Programming Language :: Python :: 3.12
Classifier: Topic :: Games/Entertainment
Classifier: Topic :: Software Development :: Libraries
Requires-Python: >=3.10
Requires-Dist: aiofiles>=23.0.0
Requires-Dist: aiohttp>=3.9.0
Requires-Dist: fastmcp>=0.1.0
Requires-Dist: pydantic>=2.0.0
Requires-Dist: python-dotenv>=1.0.0
Requires-Dist: typing-extensions>=4.8.0
